{
    "food": {
        "korean": ["된장찌개", "갈비탕", "삼계탕", "육개장", "순두부찌개", "해장국", "잡채", "떡볶이", "보쌈", "닭갈비", "고등어구이", "청국장", "수육", "안동찜닭", "돼지국밥", "통닭", "설렁탕", "오징어볶음", "김치볶음밥", "된장국", "고추장삼겹살"],
        "chinese": ["꿔바로우", "초승달", "양장피", "새우 볶음밥", "칠리 크랩", "고추잡채", "양꼬치", "훠궈", "유산슬", "소금구이 오리", "누룽지탕", "동파육", "마늘 새우", "바삭한 쇠고기", "팔보채", "피시 볼 수프", "닭발", "사천 요리"],
        "japanese": ["가츠동", "오니기리", "야키소바", "쿠시카츠", "돈부리", "샤브샤브", "스키야키", "오키노미야키", "카라아게", "나베", "미소 수프", "이자카야 스타일 요리", "와규 스테이크", "우나기", "사케", "텐푸라", "소바", "일식 카레", "에비후라이", "니코가시", "야키니쿠"],
        "western": ["리조또", "허니머스타드 치킨", "그릴드 샐몬", "피시 앤 칩스", "램버거", "클럽 샌드위치", "콜슬로", "감자 그라탕", "퀴슈", "로스트 치킨", "바비큐 리브", "미트볼", "베이글", "나초", "버팔로 윙"],
        "snack": ["핫도그", "만두", "어묵탕", "콘도그", "치즈스틱", "베이컨 감자", "토스트", "분식류 모듬", "양념 치킨", "소세지", "치즈 떡볶이", "떡볶이 피자"],
        "fast_food": ["빅맥", "치즈버거", "바베큐 치킨 버거", "피쉬 버거", "모짜렐라 인 더 버거", "치킨 랩", "감자 샐러드", "치킨 너겟", "오니언링", "치즈 프라이", "치킨 치즈 스테이크", "클래식 핫도그"],
        "healthy": ["과일 샐러드", "그레인 볼", "쿠스쿠스", "케일 샐러드", "퀴노아 볼", "오트밀", "야채 스프", "저칼로리 샌드위치", "아보카도 토스트", "단백질 쉐이크", "아사이 볼", "녹즙"],
        "vegan": ["비건 버거", "비건 피자", "비건 샐러드", "비건 라자냐", "비건 초콜릿", "비건 커리", "비건 브라우니", "비건 팬케이크", "비건 테리야키", "비건 스프", "비건 타코", "비건 스시"],
        "seafood": ["구운 생선", "해산물 파스타", "해물 라이스", "삼치 구이", "광어 회", "문어 살라다", "해물 찜", "생선 튀김", "바닷가재", "멍게 비빔밥", "해산물 피자", "해물 팟타이"],
        "bento": ["쇠고기 도시락", "새우 도시락", "야채 도시락", "연어 도시락", "텐동 도시락", "돈가스 도시락", "유부초밥 도시락", "치킨 카츠 도시락", "소바 도시락", "일식 커리 도시락", "튀김 모듬 도시락", "초밥 도시락", "숯불구이 도시락", "해산물 도시락", "비빔밥 도시락", "김치 볶음밥 도시락", "닭갈비 도시락", "오징어 볶음 도시락", "스테이크 도시락", "양념 갈비 도시락"]
    },


    "beverage": {
        "coffee": ["카푸치노", "모카", "카라멜 마키아토", "플랫 화이트", "더블 에스프레소", "콜드 브루"],
        "tea": ["백차", "우롱차", "재스민 차", "페퍼민트 차", "캐모마일 차", "레몬 그라스 차"],
        "smoothies": ["베리 스무디", "망고 스무디", "파인애플 스무디", "코코넛 밀크 스무디", "아보카도 스무디", "요거트 스무디"],
        "traditional": ["감귤차", "복분자차", "대추차", "매실차", "국화차", "홍삼차"]
    },

    "dessert": {
        "cake": ["레드 벨벳 케이크", "초콜릿 케이크", "스폰지 케이크", "바나나 케이크", "카라멜 케이크", "오레오 케이크"],
        "ice_cream": ["바닐라 아이스크림", "딸기 아이스크림", "초콜릿 아이스크림", "민트 초콜릿 칩", "쿠키 앤 크림", "캐러멜 소금 아이스크림"],
        "pastry": ["퍼프", "슈크림", "애플 파이", "타르트", "브라우니", "프레첼"],
        "traditional": ["떡", "한과", "유과", "인절미", "추억의 단팥빵", "팥죽", "무지개 떡", "꿀떡", "모시떡"]
    }

}